API.md
LICENSE
README.md
THIRD-PARTY-NOTICES
benchmark.py
fastdigest-0.9.2.dist-info/METADATA
fastdigest-0.9.2.dist-info/WHEEL
fastdigest-0.9.2.dist-info/licenses/LICENSE
fastdigest.pyi
fastdigest/__init__.py
fastdigest/__init__.pyi
fastdigest/fastdigest.pypy310-pp73-s390x-linux-gnu.so
fastdigest/py.typed
fastdigest-0.9.2.dist-info/RECORD
